fastpusher/__init__.py
fastpusher/examples.py
fastpusher/exceptions.py
fastpusher/pusher.py
fastpusher-0.1.3.dist-info/METADATA
fastpusher-0.1.3.dist-info/WHEEL
fastpusher-0.1.3.dist-info/top_level.txt
fastpusher-0.1.3.dist-info/RECORD
