Metadata-Version: 2.4
Name: fastpusher
Version: 0.1.3
Summary: A fast and efficient push notification library
Home-page: https://github.com/fastpusheruz/fastpusher
Author: FastPusherUZ
Author-email: fastpusheruz@gmail.com
License: MIT
Project-URL: Bug Reports, https://github.com/fastpusheruz/fastpusher_client/issues
Project-URL: Source, https://github.com/fastpusheruz/fastpusher_client
Project-URL: Documentation, https://github.com/fastpusheruz/fastpusher_client/wiki
Keywords: push notification messaging api rest
Classifier: Development Status :: 4 - Beta
Classifier: Intended Audience :: Developers
Classifier: License :: OSI Approved :: MIT License
Classifier: Operating System :: OS Independent
Classifier: Programming Language :: Python :: 3
Classifier: Programming Language :: Python :: 3.7
Classifier: Programming Language :: Python :: 3.8
Classifier: Programming Language :: Python :: 3.9
Classifier: Programming Language :: Python :: 3.10
Classifier: Programming Language :: Python :: 3.11
Classifier: Programming Language :: Python :: 3.12
Classifier: Topic :: Communications
Classifier: Topic :: Internet :: WWW/HTTP
Classifier: Topic :: Software Development :: Libraries :: Python Modules
Requires-Python: >=3.7.0
Requires-Dist: requests>=2.25.0
Provides-Extra: dev
Requires-Dist: pytest>=6.0.0; extra == "dev"
Requires-Dist: pytest-cov>=2.10.0; extra == "dev"
Requires-Dist: black>=21.0.0; extra == "dev"
Requires-Dist: flake8>=3.8.0; extra == "dev"
Provides-Extra: publishing
Requires-Dist: setuptools>=61.0; extra == "publishing"
Requires-Dist: wheel>=0.37.0; extra == "publishing"
Requires-Dist: twine>=4.0.0; extra == "publishing"
Requires-Dist: build>=0.8.0; extra == "publishing"
Dynamic: author
Dynamic: author-email
Dynamic: classifier
Dynamic: description
Dynamic: description-content-type
Dynamic: home-page
Dynamic: keywords
Dynamic: license
Dynamic: project-url
Dynamic: provides-extra
Dynamic: requires-dist
Dynamic: requires-python
Dynamic: summary
